pyscfad_cuda12_plugin/_solver.so
pyscfad_cuda12_plugin/version.py
pyscfad_cuda12_plugin-0.2.0.dist-info/METADATA
pyscfad_cuda12_plugin-0.2.0.dist-info/WHEEL
pyscfad_cuda12_plugin-0.2.0.dist-info/top_level.txt
pyscfad_cuda12_plugin-0.2.0.dist-info/RECORD
