Metadata-Version: 2.1
Name: pyscfad-cuda12-plugin
Version: 0.2.0
Summary: PySCFAD Plugin for NVIDIA GPUs
Author: Xing Zhang
Author-email: zhangxing.nju@gmail.com
License: Apache-2.0
Classifier: Development Status :: 3 - Alpha
Classifier: Topic :: Scientific/Engineering
Classifier: Intended Audience :: Science/Research
Classifier: License :: OSI Approved :: Apache Software License
Classifier: Programming Language :: Python :: 3.11
Classifier: Programming Language :: Python :: 3.12
Classifier: Programming Language :: Python :: 3.13
Classifier: Programming Language :: Python :: 3.14
Requires-Python: >=3.11
Provides-Extra: with_cuda
Requires-Dist: nvidia-cublas-cu12 >=12.1.3.1 ; extra == 'with_cuda'
Requires-Dist: nvidia-cuda-nvcc-cu12 >=12.6.85 ; extra == 'with_cuda'
Requires-Dist: nvidia-cuda-runtime-cu12 >=12.1.105 ; extra == 'with_cuda'
Requires-Dist: nvidia-cusolver-cu12 >=11.4.5.107 ; extra == 'with_cuda'
Requires-Dist: nvidia-cusparse-cu12 >=12.1.0.106 ; extra == 'with_cuda'
Requires-Dist: nvidia-nvjitlink-cu12 >=12.1.105 ; extra == 'with_cuda'
